{"cameraMode":{"drawMode":0,"name":"Shaded","section":"Shading Mode"},"sceneLighting":true,"audioPlay":false,"sceneViewState":{"showFog":true,"showMaterialUpdate":false,"showSkybox":true,"showFlares":true,"showImageEffects":true,"showParticleSystems":true},"in2DMode":false,"pivot":{"x":31.682085037231447,"y":-33.5535774230957,"z":-36.69384002685547},"rotation":{"x":-0.015255584381520749,"y":0.8760157823562622,"z":0.027556458488106729,"w":0.4813953936100006},"size":3.6088271141052248,"orthographic":false}